[
  {
    "id": "do_homework",
    "name": "Do Homework",
    "description": "Sit down and work through your assignments. Consistent effort builds understanding and keeps you on track.",
    "category": "education",
    "timeCost": 15,
    "skillEffects": {"intelligence": 1},
    "hiddenMetricEffects": {},
    "healthEffect": 0,
    "sectionPerformanceEffect": 8,
    "associatedHabit": null,
    "targetNpcId": null,
    "moralImpactTemplates": [],
    "educationLevel": null,
    "educationProgramId": null
  },
  {
    "id": "study_group",
    "name": "Study Group",
    "description": "Team up with classmates to review material together. Explaining concepts to others deepens your own understanding.",
    "category": "education",
    "timeCost": 20,
    "skillEffects": {"communication": 1},
    "hiddenMetricEffects": {},
    "healthEffect": 0,
    "sectionPerformanceEffect": 10,
    "associatedHabit": null,
    "targetNpcId": null,
    "moralImpactTemplates": [],
    "educationLevel": null,
    "educationProgramId": null
  },
  {
    "id": "ask_teacher_for_help",
    "name": "Ask Teacher for Help",
    "description": "Approach your teacher after class with questions. A little courage goes a long way toward clarity.",
    "category": "education",
    "timeCost": 10,
    "skillEffects": {"communication": 1},
    "hiddenMetricEffects": {},
    "healthEffect": 0,
    "sectionPerformanceEffect": 6,
    "associatedHabit": null,
    "targetNpcId": null,
    "moralImpactTemplates": [],
    "educationLevel": null,
    "educationProgramId": null
  },
  {
    "id": "visit_library",
    "name": "Visit Library",
    "description": "Spend time among the shelves, exploring books and resources beyond the syllabus. Knowledge is everywhere if you look.",
    "category": "education",
    "timeCost": 15,
    "skillEffects": {"intelligence": 2},
    "hiddenMetricEffects": {},
    "healthEffect": 0,
    "sectionPerformanceEffect": 7,
    "associatedHabit": null,
    "targetNpcId": null,
    "moralImpactTemplates": [],
    "educationLevel": null,
    "educationProgramId": null
  },
  {
    "id": "skip_class",
    "name": "Skip Class",
    "description": "Decide not to show up today. The bed is warm, but the missed lesson won't teach itself.",
    "category": "education",
    "timeCost": 5,
    "skillEffects": {},
    "hiddenMetricEffects": {},
    "healthEffect": 0,
    "sectionPerformanceEffect": -8,
    "associatedHabit": null,
    "targetNpcId": null,
    "moralImpactTemplates": [],
    "educationLevel": null,
    "educationProgramId": null
  },
  {
    "id": "procrastinate",
    "name": "Procrastinate",
    "description": "Put off studying for later, scrolling through distractions instead. Tomorrow always seems like a better day to start.",
    "category": "education",
    "timeCost": 10,
    "skillEffects": {"intelligence": -1},
    "hiddenMetricEffects": {},
    "healthEffect": 0,
    "sectionPerformanceEffect": -6,
    "associatedHabit": null,
    "targetNpcId": null,
    "moralImpactTemplates": [],
    "educationLevel": null,
    "educationProgramId": null
  },
  {
    "id": "cheat_on_test",
    "name": "Cheat on Test",
    "description": "Sneak a look at someone else's answers during the exam. The risk is high, and the knowledge gained is zero.",
    "category": "education",
    "timeCost": 5,
    "skillEffects": {},
    "hiddenMetricEffects": {},
    "healthEffect": 0,
    "sectionPerformanceEffect": -10,
    "associatedHabit": null,
    "targetNpcId": null,
    "moralImpactTemplates": [],
    "educationLevel": null,
    "educationProgramId": null
  },
  {
    "id": "oversleep_and_miss_exam",
    "name": "Oversleep and Miss Exam",
    "description": "The alarm didn't go off — or maybe you ignored it. Either way, the exam is over and you weren't there.",
    "category": "education",
    "timeCost": 5,
    "skillEffects": {},
    "hiddenMetricEffects": {},
    "healthEffect": 0,
    "sectionPerformanceEffect": -12,
    "associatedHabit": null,
    "targetNpcId": null,
    "moralImpactTemplates": [],
    "educationLevel": null,
    "educationProgramId": null
  },
  {
    "id": "finger_painting",
    "name": "Finger Painting",
    "description": "Dip your hands in bright colors and let imagination flow onto paper. Messy, joyful, and wonderfully creative.",
    "category": "education",
    "timeCost": 10,
    "skillEffects": {"creativity": 2},
    "hiddenMetricEffects": {},
    "healthEffect": 0,
    "sectionPerformanceEffect": 5,
    "associatedHabit": null,
    "targetNpcId": null,
    "moralImpactTemplates": [],
    "educationLevel": "preschool",
    "educationProgramId": null
  },
  {
    "id": "playground_games",
    "name": "Playground Games",
    "description": "Run, climb, and play with the other kids during recess. Learning to cooperate and move your body matters too.",
    "category": "education",
    "timeCost": 10,
    "skillEffects": {"fitness": 1, "communication": 1},
    "hiddenMetricEffects": {},
    "healthEffect": 0,
    "sectionPerformanceEffect": 5,
    "associatedHabit": null,
    "targetNpcId": null,
    "moralImpactTemplates": [],
    "educationLevel": "preschool",
    "educationProgramId": null
  },
  {
    "id": "throw_tantrum",
    "name": "Throw Tantrum",
    "description": "Scream, cry, and stomp your feet when things don't go your way. The whole class stops and stares.",
    "category": "education",
    "timeCost": 5,
    "skillEffects": {"emotionalStability": -1},
    "hiddenMetricEffects": {},
    "healthEffect": 0,
    "sectionPerformanceEffect": -4,
    "associatedHabit": null,
    "targetNpcId": null,
    "moralImpactTemplates": [],
    "educationLevel": "preschool",
    "educationProgramId": null
  },
  {
    "id": "refuse_to_share",
    "name": "Refuse to Share",
    "description": "Clutch the toys tightly and refuse to let anyone else play. Sharing is hard, but hoarding makes no friends.",
    "category": "education",
    "timeCost": 5,
    "skillEffects": {"communication": -1},
    "hiddenMetricEffects": {},
    "healthEffect": 0,
    "sectionPerformanceEffect": -3,
    "associatedHabit": null,
    "targetNpcId": null,
    "moralImpactTemplates": [],
    "educationLevel": "preschool",
    "educationProgramId": null
  },
  {
    "id": "join_science_fair",
    "name": "Join Science Fair",
    "description": "Build a project, form a hypothesis, and present your findings. The volcano might actually impress the judges this year.",
    "category": "education",
    "timeCost": 20,
    "skillEffects": {"intelligence": 2, "creativity": 1},
    "hiddenMetricEffects": {},
    "healthEffect": 0,
    "sectionPerformanceEffect": 8,
    "associatedHabit": null,
    "targetNpcId": null,
    "moralImpactTemplates": [],
    "educationLevel": "middleSchool",
    "educationProgramId": null
  },
  {
    "id": "practice_public_speaking",
    "name": "Practice Public Speaking",
    "description": "Stand in front of the class and deliver a presentation. Your voice shakes at first, but confidence grows with practice.",
    "category": "education",
    "timeCost": 15,
    "skillEffects": {"communication": 2},
    "hiddenMetricEffects": {},
    "healthEffect": 0,
    "sectionPerformanceEffect": 6,
    "associatedHabit": null,
    "targetNpcId": null,
    "moralImpactTemplates": [],
    "educationLevel": "middleSchool",
    "educationProgramId": null
  },
  {
    "id": "bully_classmate",
    "name": "Bully Classmate",
    "description": "Pick on someone smaller or quieter. It might feel powerful now, but cruelty leaves marks on everyone involved.",
    "category": "education",
    "timeCost": 10,
    "skillEffects": {"communication": -2},
    "hiddenMetricEffects": {},
    "healthEffect": 0,
    "sectionPerformanceEffect": -7,
    "associatedHabit": null,
    "targetNpcId": null,
    "moralImpactTemplates": [],
    "educationLevel": "middleSchool",
    "educationProgramId": null
  },
  {
    "id": "copy_homework",
    "name": "Copy Homework",
    "description": "Borrow a friend's answers and pass them off as your own. Quick and easy, but you learn absolutely nothing.",
    "category": "education",
    "timeCost": 5,
    "skillEffects": {},
    "hiddenMetricEffects": {},
    "healthEffect": 0,
    "sectionPerformanceEffect": -5,
    "associatedHabit": null,
    "targetNpcId": null,
    "moralImpactTemplates": [],
    "educationLevel": "middleSchool",
    "educationProgramId": null
  },
  {
    "id": "prepare_for_finals",
    "name": "Prepare for Finals",
    "description": "Lock yourself in with notes and flashcards for an intense study marathon. Exhausting, but your future self will thank you.",
    "category": "education",
    "timeCost": 25,
    "skillEffects": {"intelligence": 2},
    "hiddenMetricEffects": {},
    "healthEffect": -3,
    "sectionPerformanceEffect": 10,
    "associatedHabit": null,
    "targetNpcId": null,
    "moralImpactTemplates": [],
    "educationLevel": "highSchool",
    "educationProgramId": null
  },
  {
    "id": "join_academic_club",
    "name": "Join Academic Club",
    "description": "Sign up for debate, math olympiad, or another academic extracurricular. Surround yourself with curious minds.",
    "category": "education",
    "timeCost": 15,
    "skillEffects": {"creativity": 1, "communication": 1},
    "hiddenMetricEffects": {},
    "healthEffect": 0,
    "sectionPerformanceEffect": 7,
    "associatedHabit": null,
    "targetNpcId": null,
    "moralImpactTemplates": [],
    "educationLevel": "highSchool",
    "educationProgramId": null
  },
  {
    "id": "skip_school_for_party",
    "name": "Skip School for Party",
    "description": "Ditch class to hang out at someone's house party. The fun is real, but so are the consequences tomorrow.",
    "category": "education",
    "timeCost": 10,
    "skillEffects": {},
    "hiddenMetricEffects": {},
    "healthEffect": -5,
    "sectionPerformanceEffect": -9,
    "associatedHabit": null,
    "targetNpcId": null,
    "moralImpactTemplates": [],
    "educationLevel": "highSchool",
    "educationProgramId": null
  },
  {
    "id": "let_grades_slip",
    "name": "Let Grades Slip",
    "description": "Stop caring about assignments and tests. The semester drifts by while your GPA quietly sinks.",
    "category": "education",
    "timeCost": 5,
    "skillEffects": {},
    "hiddenMetricEffects": {},
    "healthEffect": 0,
    "sectionPerformanceEffect": -8,
    "associatedHabit": null,
    "targetNpcId": null,
    "moralImpactTemplates": [],
    "educationLevel": "highSchool",
    "educationProgramId": null
  },
  {
    "id": "attend_office_hours",
    "name": "Attend Office Hours",
    "description": "Visit your professor during their open hours to discuss coursework. One-on-one guidance can unlock new understanding.",
    "category": "education",
    "timeCost": 15,
    "skillEffects": {"intelligence": 1},
    "hiddenMetricEffects": {},
    "healthEffect": 0,
    "sectionPerformanceEffect": 8,
    "associatedHabit": null,
    "targetNpcId": null,
    "moralImpactTemplates": [],
    "educationLevel": "university",
    "educationProgramId": null
  },
  {
    "id": "write_research_paper",
    "name": "Write Research Paper",
    "description": "Pour hours into drafting, citing, and revising an original paper. Academic writing is grueling but deeply rewarding.",
    "category": "education",
    "timeCost": 25,
    "skillEffects": {"intelligence": 2, "creativity": 1},
    "hiddenMetricEffects": {},
    "healthEffect": 0,
    "sectionPerformanceEffect": 10,
    "associatedHabit": null,
    "targetNpcId": null,
    "moralImpactTemplates": [],
    "educationLevel": "university",
    "educationProgramId": null
  },
  {
    "id": "party_before_exams",
    "name": "Party Before Exams",
    "description": "Hit the bars the night before a major exam. The hangover will be the least of your problems tomorrow morning.",
    "category": "education",
    "timeCost": 15,
    "skillEffects": {},
    "hiddenMetricEffects": {},
    "healthEffect": -5,
    "sectionPerformanceEffect": -10,
    "associatedHabit": null,
    "targetNpcId": null,
    "moralImpactTemplates": [],
    "educationLevel": "university",
    "educationProgramId": null
  },
  {
    "id": "plagiarize_assignment",
    "name": "Plagiarize Assignment",
    "description": "Copy text from online sources and submit it as your own work. If caught, the academic consequences are severe.",
    "category": "education",
    "timeCost": 5,
    "skillEffects": {},
    "hiddenMetricEffects": {},
    "healthEffect": 0,
    "sectionPerformanceEffect": -12,
    "associatedHabit": null,
    "targetNpcId": null,
    "moralImpactTemplates": [],
    "educationLevel": "university",
    "educationProgramId": null
  },
  {
    "id": "present_at_conference",
    "name": "Present at Conference",
    "description": "Stand before peers and experts to share your research findings. Nerve-wracking, but it establishes your academic voice.",
    "category": "education",
    "timeCost": 20,
    "skillEffects": {"communication": 2, "intelligence": 1},
    "hiddenMetricEffects": {},
    "healthEffect": 0,
    "sectionPerformanceEffect": 10,
    "associatedHabit": null,
    "targetNpcId": null,
    "moralImpactTemplates": [],
    "educationLevel": "master",
    "educationProgramId": null
  },
  {
    "id": "publish_journal_article",
    "name": "Publish Journal Article",
    "description": "Submit your research to a peer-reviewed journal and see it through to publication. A milestone in any academic career.",
    "category": "education",
    "timeCost": 25,
    "skillEffects": {"intelligence": 2},
    "hiddenMetricEffects": {},
    "healthEffect": 0,
    "sectionPerformanceEffect": 12,
    "associatedHabit": null,
    "targetNpcId": null,
    "moralImpactTemplates": [],
    "educationLevel": "master",
    "educationProgramId": null
  },
  {
    "id": "neglect_thesis",
    "name": "Neglect Thesis",
    "description": "Let weeks pass without touching your thesis draft. The deadline looms larger with every day of avoidance.",
    "category": "education",
    "timeCost": 5,
    "skillEffects": {},
    "hiddenMetricEffects": {},
    "healthEffect": 0,
    "sectionPerformanceEffect": -10,
    "associatedHabit": null,
    "targetNpcId": null,
    "moralImpactTemplates": [],
    "educationLevel": "master",
    "educationProgramId": null
  },
  {
    "id": "argue_with_advisor",
    "name": "Argue with Advisor",
    "description": "Clash with your thesis advisor over direction and methodology. Burning bridges with your mentor rarely ends well.",
    "category": "education",
    "timeCost": 10,
    "skillEffects": {"communication": -1},
    "hiddenMetricEffects": {},
    "healthEffect": 0,
    "sectionPerformanceEffect": -8,
    "associatedHabit": null,
    "targetNpcId": null,
    "moralImpactTemplates": [],
    "educationLevel": "master",
    "educationProgramId": null
  },
  {
    "id": "breakthrough_research",
    "name": "Breakthrough Research",
    "description": "After months of dead ends, a flash of insight connects everything. This could change the field — and your career.",
    "category": "education",
    "timeCost": 25,
    "skillEffects": {"intelligence": 3, "creativity": 1},
    "hiddenMetricEffects": {},
    "healthEffect": 0,
    "sectionPerformanceEffect": 15,
    "associatedHabit": null,
    "targetNpcId": null,
    "moralImpactTemplates": [],
    "educationLevel": "doctorate",
    "educationProgramId": null
  },
  {
    "id": "teach_undergraduate_class",
    "name": "Teach Undergraduate Class",
    "description": "Step into the lecturer's role and teach a session to undergrads. Teaching others solidifies your own mastery.",
    "category": "education",
    "timeCost": 20,
    "skillEffects": {"communication": 2},
    "hiddenMetricEffects": {},
    "healthEffect": 0,
    "sectionPerformanceEffect": 8,
    "associatedHabit": null,
    "targetNpcId": null,
    "moralImpactTemplates": [],
    "educationLevel": "doctorate",
    "educationProgramId": null
  },
  {
    "id": "fabricate_data",
    "name": "Fabricate Data",
    "description": "Invent research results that never existed. If discovered, it will destroy your reputation and career entirely.",
    "category": "education",
    "timeCost": 5,
    "skillEffects": {"intelligence": -2},
    "hiddenMetricEffects": {},
    "healthEffect": 0,
    "sectionPerformanceEffect": -15,
    "associatedHabit": null,
    "targetNpcId": null,
    "moralImpactTemplates": [],
    "educationLevel": "doctorate",
    "educationProgramId": null
  },
  {
    "id": "dissertation_writers_block",
    "name": "Dissertation Writer's Block",
    "description": "Stare at a blinking cursor for hours, unable to write a single paragraph. The pressure mounts and sleep suffers.",
    "category": "education",
    "timeCost": 10,
    "skillEffects": {"creativity": -1},
    "hiddenMetricEffects": {},
    "healthEffect": -3,
    "sectionPerformanceEffect": -8,
    "associatedHabit": null,
    "targetNpcId": null,
    "moralImpactTemplates": [],
    "educationLevel": "doctorate",
    "educationProgramId": null
  },
  {
    "id": "practice_mock_trial",
    "name": "Practice Mock Trial",
    "description": "Argue a simulated case before mock judges and opposing counsel. Sharpen your rhetoric and think on your feet.",
    "category": "education",
    "timeCost": 15,
    "skillEffects": {"communication": 2},
    "hiddenMetricEffects": {},
    "healthEffect": 0,
    "sectionPerformanceEffect": 8,
    "associatedHabit": null,
    "targetNpcId": null,
    "moralImpactTemplates": [],
    "educationLevel": "university",
    "educationProgramId": "uni_law"
  },
  {
    "id": "miss_court_observation",
    "name": "Miss Court Observation",
    "description": "Skip the mandatory courtroom visit. Your professor noticed your empty seat, and the real-world lesson is lost.",
    "category": "education",
    "timeCost": 5,
    "skillEffects": {},
    "hiddenMetricEffects": {},
    "healthEffect": 0,
    "sectionPerformanceEffect": -7,
    "associatedHabit": null,
    "targetNpcId": null,
    "moralImpactTemplates": [],
    "educationLevel": "university",
    "educationProgramId": "uni_law"
  },
  {
    "id": "write_literary_analysis",
    "name": "Write Literary Analysis",
    "description": "Craft a thoughtful essay dissecting themes, symbols, and narrative technique in a classic work of literature.",
    "category": "education",
    "timeCost": 20,
    "skillEffects": {"creativity": 2},
    "hiddenMetricEffects": {},
    "healthEffect": 0,
    "sectionPerformanceEffect": 8,
    "associatedHabit": null,
    "targetNpcId": null,
    "moralImpactTemplates": [],
    "educationLevel": "university",
    "educationProgramId": "uni_literature"
  },
  {
    "id": "ignore_reading_list",
    "name": "Ignore Reading List",
    "description": "Let the assigned novels pile up unread on your desk. Class discussions become a minefield of things you don't know.",
    "category": "education",
    "timeCost": 5,
    "skillEffects": {"intelligence": -1},
    "hiddenMetricEffects": {},
    "healthEffect": 0,
    "sectionPerformanceEffect": -6,
    "associatedHabit": null,
    "targetNpcId": null,
    "moralImpactTemplates": [],
    "educationLevel": "university",
    "educationProgramId": "uni_literature"
  },
  {
    "id": "archive_research",
    "name": "Archive Research",
    "description": "Spend the day in dusty archives, carefully examining primary sources and piecing together fragments of the past.",
    "category": "education",
    "timeCost": 20,
    "skillEffects": {"intelligence": 2},
    "hiddenMetricEffects": {},
    "healthEffect": 0,
    "sectionPerformanceEffect": 8,
    "associatedHabit": null,
    "targetNpcId": null,
    "moralImpactTemplates": [],
    "educationLevel": "university",
    "educationProgramId": "uni_history"
  },
  {
    "id": "skip_field_trip",
    "name": "Skip Field Trip",
    "description": "Stay home instead of visiting the historical site with your class. You'll never get that firsthand experience back.",
    "category": "education",
    "timeCost": 5,
    "skillEffects": {},
    "hiddenMetricEffects": {},
    "healthEffect": 0,
    "sectionPerformanceEffect": -6,
    "associatedHabit": null,
    "targetNpcId": null,
    "moralImpactTemplates": [],
    "educationLevel": "university",
    "educationProgramId": "uni_history"
  },
  {
    "id": "practice_programming",
    "name": "Practice Programming",
    "description": "Grind through coding exercises and build small projects. Every bug you fix makes you a sharper programmer.",
    "category": "education",
    "timeCost": 20,
    "skillEffects": {"intelligence": 2, "creativity": 1},
    "hiddenMetricEffects": {},
    "healthEffect": 0,
    "sectionPerformanceEffect": 10,
    "associatedHabit": null,
    "targetNpcId": null,
    "moralImpactTemplates": [],
    "educationLevel": "university",
    "educationProgramId": "uni_cs"
  },
  {
    "id": "ignore_debugging",
    "name": "Ignore Debugging",
    "description": "Submit code riddled with bugs without bothering to test it. The compiler errors will speak for themselves.",
    "category": "education",
    "timeCost": 5,
    "skillEffects": {"intelligence": -1},
    "hiddenMetricEffects": {},
    "healthEffect": 0,
    "sectionPerformanceEffect": -8,
    "associatedHabit": null,
    "targetNpcId": null,
    "moralImpactTemplates": [],
    "educationLevel": "university",
    "educationProgramId": "uni_cs"
  },
  {
    "id": "design_project",
    "name": "Design Project",
    "description": "Sketch blueprints and run calculations for an original engineering design. Turning ideas into structures starts here.",
    "category": "education",
    "timeCost": 25,
    "skillEffects": {"creativity": 2, "intelligence": 1},
    "hiddenMetricEffects": {},
    "healthEffect": 0,
    "sectionPerformanceEffect": 10,
    "associatedHabit": null,
    "targetNpcId": null,
    "moralImpactTemplates": [],
    "educationLevel": "university",
    "educationProgramId": "uni_engineering"
  },
  {
    "id": "skip_lab_session",
    "name": "Skip Lab Session",
    "description": "Blow off the hands-on lab where theory meets practice. Reading about circuits is no substitute for building them.",
    "category": "education",
    "timeCost": 5,
    "skillEffects": {},
    "hiddenMetricEffects": {},
    "healthEffect": 0,
    "sectionPerformanceEffect": -8,
    "associatedHabit": null,
    "targetNpcId": null,
    "moralImpactTemplates": [],
    "educationLevel": "university",
    "educationProgramId": "uni_engineering"
  },
  {
    "id": "clinical_rotation",
    "name": "Clinical Rotation",
    "description": "Shadow doctors in a hospital ward, observing real patients and procedures. Medicine comes alive beyond the textbook.",
    "category": "education",
    "timeCost": 25,
    "skillEffects": {"intelligence": 1, "communication": 1},
    "hiddenMetricEffects": {},
    "healthEffect": 0,
    "sectionPerformanceEffect": 10,
    "associatedHabit": null,
    "targetNpcId": null,
    "moralImpactTemplates": [],
    "educationLevel": "university",
    "educationProgramId": "uni_medicine"
  },
  {
    "id": "skip_anatomy_lab",
    "name": "Skip Anatomy Lab",
    "description": "Avoid the dissection lab because it's unpleasant. But you can't become a doctor without knowing what's inside.",
    "category": "education",
    "timeCost": 5,
    "skillEffects": {},
    "hiddenMetricEffects": {},
    "healthEffect": 0,
    "sectionPerformanceEffect": -10,
    "associatedHabit": null,
    "targetNpcId": null,
    "moralImpactTemplates": [],
    "educationLevel": "university",
    "educationProgramId": "uni_medicine"
  },
  {
    "id": "analyze_court_cases",
    "name": "Analyze Court Cases",
    "description": "Dissect landmark constitutional rulings, tracing the reasoning that shaped the law of the land.",
    "category": "education",
    "timeCost": 20,
    "skillEffects": {"intelligence": 2},
    "hiddenMetricEffects": {},
    "healthEffect": 0,
    "sectionPerformanceEffect": 10,
    "associatedHabit": null,
    "targetNpcId": null,
    "moralImpactTemplates": [],
    "educationLevel": "master",
    "educationProgramId": "master_constitutional_law"
  },
  {
    "id": "skip_diplomacy_seminar",
    "name": "Skip Diplomacy Seminar",
    "description": "Miss the seminar on international treaty negotiation. The nuances of diplomacy won't learn themselves.",
    "category": "education",
    "timeCost": 5,
    "skillEffects": {},
    "hiddenMetricEffects": {},
    "healthEffect": 0,
    "sectionPerformanceEffect": -8,
    "associatedHabit": null,
    "targetNpcId": null,
    "moralImpactTemplates": [],
    "educationLevel": "master",
    "educationProgramId": "master_international_law"
  },
  {
    "id": "complete_manuscript_chapter",
    "name": "Complete Manuscript Chapter",
    "description": "Finish a full chapter of your creative manuscript. Every polished page brings the story closer to life.",
    "category": "education",
    "timeCost": 20,
    "skillEffects": {"creativity": 2},
    "hiddenMetricEffects": {},
    "healthEffect": 0,
    "sectionPerformanceEffect": 10,
    "associatedHabit": null,
    "targetNpcId": null,
    "moralImpactTemplates": [],
    "educationLevel": "master",
    "educationProgramId": "master_creative_writing"
  },
  {
    "id": "neglect_translation_work",
    "name": "Neglect Translation Work",
    "description": "Leave your comparative translation assignments untouched. The languages won't bridge themselves across cultures.",
    "category": "education",
    "timeCost": 5,
    "skillEffects": {"intelligence": -1},
    "hiddenMetricEffects": {},
    "healthEffect": 0,
    "sectionPerformanceEffect": -8,
    "associatedHabit": null,
    "targetNpcId": null,
    "moralImpactTemplates": [],
    "educationLevel": "master",
    "educationProgramId": "master_comparative_literature"
  },
  {
    "id": "excavation_fieldwork",
    "name": "Excavation Fieldwork",
    "description": "Dig at an archaeological site under the hot sun, carefully brushing away centuries of earth to reveal history beneath.",
    "category": "education",
    "timeCost": 25,
    "skillEffects": {"fitness": 1, "intelligence": 1},
    "hiddenMetricEffects": {},
    "healthEffect": 0,
    "sectionPerformanceEffect": 10,
    "associatedHabit": null,
    "targetNpcId": null,
    "moralImpactTemplates": [],
    "educationLevel": "master",
    "educationProgramId": "master_ancient_history"
  },
  {
    "id": "miss_archive_deadline",
    "name": "Miss Archive Deadline",
    "description": "Fail to submit your archival research request on time. The documents you needed are now locked away for months.",
    "category": "education",
    "timeCost": 5,
    "skillEffects": {},
    "hiddenMetricEffects": {},
    "healthEffect": 0,
    "sectionPerformanceEffect": -8,
    "associatedHabit": null,
    "targetNpcId": null,
    "moralImpactTemplates": [],
    "educationLevel": "master",
    "educationProgramId": "master_modern_history"
  },
  {
    "id": "train_neural_network",
    "name": "Train Neural Network",
    "description": "Configure hyperparameters and run training epochs on your model. Watching the loss curve drop is deeply satisfying.",
    "category": "education",
    "timeCost": 25,
    "skillEffects": {"intelligence": 2},
    "hiddenMetricEffects": {},
    "healthEffect": 0,
    "sectionPerformanceEffect": 12,
    "associatedHabit": null,
    "targetNpcId": null,
    "moralImpactTemplates": [],
    "educationLevel": "master",
    "educationProgramId": "master_ai"
  },
  {
    "id": "ignore_security_audit",
    "name": "Ignore Security Audit",
    "description": "Skip the scheduled security review of your system. Vulnerabilities don't fix themselves, and attackers won't wait.",
    "category": "education",
    "timeCost": 5,
    "skillEffects": {},
    "hiddenMetricEffects": {},
    "healthEffect": 0,
    "sectionPerformanceEffect": -10,
    "associatedHabit": null,
    "targetNpcId": null,
    "moralImpactTemplates": [],
    "educationLevel": "master",
    "educationProgramId": "master_cybersecurity"
  },
  {
    "id": "prototype_robot",
    "name": "Prototype Robot",
    "description": "Assemble servos, sensors, and code into a working robot prototype. When it moves on its own, the thrill is electric.",
    "category": "education",
    "timeCost": 25,
    "skillEffects": {"creativity": 2, "intelligence": 1},
    "hiddenMetricEffects": {},
    "healthEffect": 0,
    "sectionPerformanceEffect": 10,
    "associatedHabit": null,
    "targetNpcId": null,
    "moralImpactTemplates": [],
    "educationLevel": "master",
    "educationProgramId": "master_robotics"
  },
  {
    "id": "skip_site_inspection",
    "name": "Skip Site Inspection",
    "description": "Miss the mandatory construction site visit. Engineering without fieldwork is theory without grounding.",
    "category": "education",
    "timeCost": 5,
    "skillEffects": {},
    "hiddenMetricEffects": {},
    "healthEffect": 0,
    "sectionPerformanceEffect": -8,
    "associatedHabit": null,
    "targetNpcId": null,
    "moralImpactTemplates": [],
    "educationLevel": "master",
    "educationProgramId": "master_civil_engineering"
  },
  {
    "id": "perform_supervised_surgery",
    "name": "Perform Supervised Surgery",
    "description": "Operate on a patient under the watchful eye of an attending surgeon. Steady hands and sharp focus save lives.",
    "category": "education",
    "timeCost": 25,
    "skillEffects": {"intelligence": 1},
    "hiddenMetricEffects": {},
    "healthEffect": 0,
    "sectionPerformanceEffect": 12,
    "associatedHabit": null,
    "targetNpcId": null,
    "moralImpactTemplates": [],
    "educationLevel": "master",
    "educationProgramId": "master_surgery"
  },
  {
    "id": "miss_brain_scan_analysis",
    "name": "Miss Brain Scan Analysis",
    "description": "Fail to review the fMRI data your lab collected. Weeks of scanning time go to waste without proper analysis.",
    "category": "education",
    "timeCost": 5,
    "skillEffects": {"intelligence": -1},
    "hiddenMetricEffects": {},
    "healthEffect": 0,
    "sectionPerformanceEffect": -8,
    "associatedHabit": null,
    "targetNpcId": null,
    "moralImpactTemplates": [],
    "educationLevel": "master",
    "educationProgramId": "master_neuroscience"
  },
  {
    "id": "publish_constitutional_review",
    "name": "Publish Constitutional Review",
    "description": "Your analysis of constitutional doctrine is accepted by a prestigious law review. A defining academic achievement.",
    "category": "education",
    "timeCost": 25,
    "skillEffects": {"intelligence": 2},
    "hiddenMetricEffects": {},
    "healthEffect": 0,
    "sectionPerformanceEffect": 12,
    "associatedHabit": null,
    "targetNpcId": null,
    "moralImpactTemplates": [],
    "educationLevel": "doctorate",
    "educationProgramId": "phd_constitutional_law"
  },
  {
    "id": "miss_treaty_conference",
    "name": "Miss Treaty Conference",
    "description": "Skip the international law conference where leading scholars present. Networking opportunities and insights slip away.",
    "category": "education",
    "timeCost": 5,
    "skillEffects": {},
    "hiddenMetricEffects": {},
    "healthEffect": 0,
    "sectionPerformanceEffect": -10,
    "associatedHabit": null,
    "targetNpcId": null,
    "moralImpactTemplates": [],
    "educationLevel": "doctorate",
    "educationProgramId": "phd_international_law"
  },
  {
    "id": "finish_creative_thesis_chapter",
    "name": "Finish Creative Thesis Chapter",
    "description": "Complete a chapter of your creative doctoral thesis. The prose sings, and your committee will notice the quality.",
    "category": "education",
    "timeCost": 25,
    "skillEffects": {"creativity": 2},
    "hiddenMetricEffects": {},
    "healthEffect": 0,
    "sectionPerformanceEffect": 12,
    "associatedHabit": null,
    "targetNpcId": null,
    "moralImpactTemplates": [],
    "educationLevel": "doctorate",
    "educationProgramId": "phd_creative_writing"
  },
  {
    "id": "abandon_translation_project",
    "name": "Abandon Translation Project",
    "description": "Give up on your comparative translation dissertation project halfway through. Months of work left unfinished.",
    "category": "education",
    "timeCost": 5,
    "skillEffects": {"creativity": -1},
    "hiddenMetricEffects": {},
    "healthEffect": 0,
    "sectionPerformanceEffect": -10,
    "associatedHabit": null,
    "targetNpcId": null,
    "moralImpactTemplates": [],
    "educationLevel": "doctorate",
    "educationProgramId": "phd_comparative_literature"
  },
  {
    "id": "discover_artifact",
    "name": "Discover Artifact",
    "description": "Unearth a significant artifact during your doctoral excavation. A find like this could rewrite a chapter of history.",
    "category": "education",
    "timeCost": 25,
    "skillEffects": {"intelligence": 2, "creativity": 1},
    "hiddenMetricEffects": {},
    "healthEffect": 0,
    "sectionPerformanceEffect": 15,
    "associatedHabit": null,
    "targetNpcId": null,
    "moralImpactTemplates": [],
    "educationLevel": "doctorate",
    "educationProgramId": "phd_ancient_history"
  },
  {
    "id": "lose_research_notes",
    "name": "Lose Research Notes",
    "description": "Misplace months of handwritten research notes with no backup. The sinking feeling is indescribable.",
    "category": "education",
    "timeCost": 5,
    "skillEffects": {},
    "hiddenMetricEffects": {},
    "healthEffect": 0,
    "sectionPerformanceEffect": -12,
    "associatedHabit": null,
    "targetNpcId": null,
    "moralImpactTemplates": [],
    "educationLevel": "doctorate",
    "educationProgramId": "phd_modern_history"
  },
  {
    "id": "develop_novel_algorithm",
    "name": "Develop Novel Algorithm",
    "description": "Design a new machine learning algorithm that outperforms existing benchmarks. This is what doctoral research dreams are made of.",
    "category": "education",
    "timeCost": 25,
    "skillEffects": {"intelligence": 3},
    "hiddenMetricEffects": {},
    "healthEffect": 0,
    "sectionPerformanceEffect": 15,
    "associatedHabit": null,
    "targetNpcId": null,
    "moralImpactTemplates": [],
    "educationLevel": "doctorate",
    "educationProgramId": "phd_machine_learning"
  },
  {
    "id": "fail_penetration_test",
    "name": "Fail Penetration Test",
    "description": "Your security system is breached during a controlled test. Back to the drawing board with your defense strategy.",
    "category": "education",
    "timeCost": 5,
    "skillEffects": {"intelligence": -1},
    "hiddenMetricEffects": {},
    "healthEffect": 0,
    "sectionPerformanceEffect": -10,
    "associatedHabit": null,
    "targetNpcId": null,
    "moralImpactTemplates": [],
    "educationLevel": "doctorate",
    "educationProgramId": "phd_security_systems"
  },
  {
    "id": "successful_autonomous_test",
    "name": "Successful Autonomous Test",
    "description": "Your autonomous system navigates the test course flawlessly. Months of calibration and coding pay off in one perfect run.",
    "category": "education",
    "timeCost": 25,
    "skillEffects": {"intelligence": 2, "creativity": 1},
    "hiddenMetricEffects": {},
    "healthEffect": 0,
    "sectionPerformanceEffect": 15,
    "associatedHabit": null,
    "targetNpcId": null,
    "moralImpactTemplates": [],
    "educationLevel": "doctorate",
    "educationProgramId": "phd_autonomous_systems"
  },
  {
    "id": "miscalculate_load_bearing",
    "name": "Miscalculate Load Bearing",
    "description": "A critical error in your structural calculations is caught during review. In the real world, this mistake could be catastrophic.",
    "category": "education",
    "timeCost": 5,
    "skillEffects": {"intelligence": -1},
    "hiddenMetricEffects": {},
    "healthEffect": 0,
    "sectionPerformanceEffect": -12,
    "associatedHabit": null,
    "targetNpcId": null,
    "moralImpactTemplates": [],
    "educationLevel": "doctorate",
    "educationProgramId": "phd_structural_engineering"
  },
  {
    "id": "pioneer_new_technique",
    "name": "Pioneer New Technique",
    "description": "Develop an innovative surgical technique that reduces recovery time. Your name will be attached to this procedure forever.",
    "category": "education",
    "timeCost": 25,
    "skillEffects": {"intelligence": 2},
    "hiddenMetricEffects": {},
    "healthEffect": 0,
    "sectionPerformanceEffect": 15,
    "associatedHabit": null,
    "targetNpcId": null,
    "moralImpactTemplates": [],
    "educationLevel": "doctorate",
    "educationProgramId": "phd_surgical_innovation"
  },
  {
    "id": "contaminate_brain_samples",
    "name": "Contaminate Brain Samples",
    "description": "Accidentally contaminate irreplaceable brain tissue samples through careless handling. Months of collection ruined in an instant.",
    "category": "education",
    "timeCost": 5,
    "skillEffects": {"intelligence": -1},
    "hiddenMetricEffects": {},
    "healthEffect": 0,
    "sectionPerformanceEffect": -12,
    "associatedHabit": null,
    "targetNpcId": null,
    "moralImpactTemplates": [],
    "educationLevel": "doctorate",
    "educationProgramId": "phd_cognitive_neuroscience"
  }
]
